[{"outputType":{"type":"APK"},"apkData":{"type":"FULL_SPLIT","splits":[{"filterType":"ABI","value":"arm64-v8a"}],"versionCode":1,"versionName":"1.0","enabled":true,"filterName":"arm64-v8a","outputFile":"app-arm64-v8a-debug.apk","fullName":"arm64-v8aDebug","baseName":"arm64-v8a-debug","dirName":"arm64-v8a/"},"path":"app-arm64-v8a-debug.apk","properties":{}},{"outputType":{"type":"APK"},"apkData":{"type":"FULL_SPLIT","splits":[{"filterType":"ABI","value":"armeabi-v7a"},{"filterType":"DENSITY","value":"hdpi"}],"versionCode":1,"versionName":"1.0","enabled":true,"filterName":"hdpiArmeabi-v7a","outputFile":"app-hdpiArmeabi-v7a-debug.apk","fullName":"hdpiArmeabi-v7aDebug","baseName":"hdpiArmeabi-v7a-debug","dirName":"armeabi-v7a/hdpi/"},"path":"app-hdpiArmeabi-v7a-debug.apk","properties":{}},{"outputType":{"type":"APK"},"apkData":{"type":"FULL_SPLIT","splits":[{"filterType":"ABI","value":"arm64-v8a"},{"filterType":"DENSITY","value":"hdpi"}],"versionCode":1,"versionName":"1.0","enabled":true,"filterName":"hdpiArm64-v8a","outputFile":"app-hdpiArm64-v8a-debug.apk","fullName":"hdpiArm64-v8aDebug","baseName":"hdpiArm64-v8a-debug","dirName":"arm64-v8a/hdpi/"},"path":"app-hdpiArm64-v8a-debug.apk","properties":{}},{"outputType":{"type":"APK"},"apkData":{"type":"FULL_SPLIT","splits":[{"filterType":"ABI","value":"armeabi-v7a"}],"versionCode":1,"versionName":"1.0","enabled":true,"filterName":"armeabi-v7a","outputFile":"app-armeabi-v7a-debug.apk","fullName":"armeabi-v7aDebug","baseName":"armeabi-v7a-debug","dirName":"armeabi-v7a/"},"path":"app-armeabi-v7a-debug.apk","properties":{}},{"outputType":{"type":"APK"},"apkData":{"type":"FULL_SPLIT","splits":[{"filterType":"ABI","value":"x86"},{"filterType":"DENSITY","value":"hdpi"}],"versionCode":1,"versionName":"1.0","enabled":true,"filterName":"hdpiX86","outputFile":"app-hdpiX86-debug.apk","fullName":"hdpiX86Debug","baseName":"hdpiX86-debug","dirName":"x86/hdpi/"},"path":"app-hdpiX86-debug.apk","properties":{}},{"outputType":{"type":"APK"},"apkData":{"type":"FULL_SPLIT","splits":[{"filterType":"ABI","value":"x86_64"},{"filterType":"DENSITY","value":"hdpi"}],"versionCode":1,"versionName":"1.0","enabled":true,"filterName":"hdpiX86_64","outputFile":"app-hdpiX86_64-debug.apk","fullName":"hdpiX86_64Debug","baseName":"hdpiX86_64-debug","dirName":"x86_64/hdpi/"},"path":"app-hdpiX86_64-debug.apk","properties":{}},{"outputType":{"type":"APK"},"apkData":{"type":"FULL_SPLIT","splits":[{"filterType":"ABI","value":"arm64-v8a"},{"filterType":"DENSITY","value":"mdpi"}],"versionCode":1,"versionName":"1.0","enabled":true,"filterName":"mdpiArm64-v8a","outputFile":"app-mdpiArm64-v8a-debug.apk","fullName":"mdpiArm64-v8aDebug","baseName":"mdpiArm64-v8a-debug","dirName":"arm64-v8a/mdpi/"},"path":"app-mdpiArm64-v8a-debug.apk","properties":{}},{"outputType":{"type":"APK"},"apkData":{"type":"FULL_SPLIT","splits":[{"filterType":"ABI","value":"armeabi-v7a"},{"filterType":"DENSITY","value":"mdpi"}],"versionCode":1,"versionName":"1.0","enabled":true,"filterName":"mdpiArmeabi-v7a","outputFile":"app-mdpiArmeabi-v7a-debug.apk","fullName":"mdpiArmeabi-v7aDebug","baseName":"mdpiArmeabi-v7a-debug","dirName":"armeabi-v7a/mdpi/"},"path":"app-mdpiArmeabi-v7a-debug.apk","properties":{}},{"outputType":{"type":"APK"},"apkData":{"type":"FULL_SPLIT","splits":[{"filterType":"ABI","value":"x86"},{"filterType":"DENSITY","value":"mdpi"}],"versionCode":1,"versionName":"1.0","enabled":true,"filterName":"mdpiX86","outputFile":"app-mdpiX86-debug.apk","fullName":"mdpiX86Debug","baseName":"mdpiX86-debug","dirName":"x86/mdpi/"},"path":"app-mdpiX86-debug.apk","properties":{}},{"outputType":{"type":"APK"},"apkData":{"type":"FULL_SPLIT","splits":[{"filterType":"ABI","value":"x86_64"},{"filterType":"DENSITY","value":"mdpi"}],"versionCode":1,"versionName":"1.0","enabled":true,"filterName":"mdpiX86_64","outputFile":"app-mdpiX86_64-debug.apk","fullName":"mdpiX86_64Debug","baseName":"mdpiX86_64-debug","dirName":"x86_64/mdpi/"},"path":"app-mdpiX86_64-debug.apk","properties":{}},{"outputType":{"type":"APK"},"apkData":{"type":"FULL_SPLIT","splits":[{"filterType":"ABI","value":"x86"}],"versionCode":1,"versionName":"1.0","enabled":true,"filterName":"x86","outputFile":"app-x86-debug.apk","fullName":"x86Debug","baseName":"x86-debug","dirName":"x86/"},"path":"app-x86-debug.apk","properties":{}},{"outputType":{"type":"APK"},"apkData":{"type":"FULL_SPLIT","splits":[{"filterType":"ABI","value":"arm64-v8a"},{"filterType":"DENSITY","value":"xhdpi"}],"versionCode":1,"versionName":"1.0","enabled":true,"filterName":"xhdpiArm64-v8a","outputFile":"app-xhdpiArm64-v8a-debug.apk","fullName":"xhdpiArm64-v8aDebug","baseName":"xhdpiArm64-v8a-debug","dirName":"arm64-v8a/xhdpi/"},"path":"app-xhdpiArm64-v8a-debug.apk","properties":{}},{"outputType":{"type":"APK"},"apkData":{"type":"FULL_SPLIT","splits":[{"filterType":"ABI","value":"x86_64"}],"versionCode":1,"versionName":"1.0","enabled":true,"filterName":"x86_64","outputFile":"app-x86_64-debug.apk","fullName":"x86_64Debug","baseName":"x86_64-debug","dirName":"x86_64/"},"path":"app-x86_64-debug.apk","properties":{}},{"outputType":{"type":"APK"},"apkData":{"type":"FULL_SPLIT","splits":[{"filterType":"ABI","value":"armeabi-v7a"},{"filterType":"DENSITY","value":"xhdpi"}],"versionCode":1,"versionName":"1.0","enabled":true,"filterName":"xhdpiArmeabi-v7a","outputFile":"app-xhdpiArmeabi-v7a-debug.apk","fullName":"xhdpiArmeabi-v7aDebug","baseName":"xhdpiArmeabi-v7a-debug","dirName":"armeabi-v7a/xhdpi/"},"path":"app-xhdpiArmeabi-v7a-debug.apk","properties":{}},{"outputType":{"type":"APK"},"apkData":{"type":"FULL_SPLIT","splits":[{"filterType":"ABI","value":"x86"},{"filterType":"DENSITY","value":"xhdpi"}],"versionCode":1,"versionName":"1.0","enabled":true,"filterName":"xhdpiX86","outputFile":"app-xhdpiX86-debug.apk","fullName":"xhdpiX86Debug","baseName":"xhdpiX86-debug","dirName":"x86/xhdpi/"},"path":"app-xhdpiX86-debug.apk","properties":{}},{"outputType":{"type":"APK"},"apkData":{"type":"FULL_SPLIT","splits":[{"filterType":"ABI","value":"x86_64"},{"filterType":"DENSITY","value":"xhdpi"}],"versionCode":1,"versionName":"1.0","enabled":true,"filterName":"xhdpiX86_64","outputFile":"app-xhdpiX86_64-debug.apk","fullName":"xhdpiX86_64Debug","baseName":"xhdpiX86_64-debug","dirName":"x86_64/xhdpi/"},"path":"app-xhdpiX86_64-debug.apk","properties":{}}]